[
    {
        "name": "Tobirama Senju",
        "team": "alliance",
        "hp": 72,
        "mp": 22,
        "extra_mp": null,
        "xp": 5,
        "available_from_turn": 1,
        "available_until_turn": 3,
        "roster_image": "tobirama_senju.png"
    },
    {
        "name": "Hashirama Senju",
        "team": "alliance",
        "hp": 74,
        "mp": 23,
        "extra_mp": null,
        "xp": 5,
        "available_from_turn": 1,
        "available_until_turn": 4,
        "roster_image": "hashirama_senju.png"
    },
    {
        "name": "Minato Namikaze",
        "team": "alliance",
        "hp": 75,
        "mp": 24,
        "extra_mp": 2,
        "xp": 5,
        "available_from_turn": 2,
        "available_until_turn": 2,
        "roster_image": "minato_namikaze.png"
    },
    {
        "name": "Mei Terumi",
        "team": "akatsuki",
        "hp": 57,
        "mp": 17,
        "extra_mp": null,
        "xp": 4,
        "available_from_turn": 1,
        "available_until_turn": null,
        "roster_image": "mei_terumi.png"
    },
    {
        "name": "Tsunade",
        "team": "akatsuki",
        "hp": 58,
        "mp": 17,
        "extra_mp": null,
        "xp": 4,
        "available_from_turn": 1,
        "available_until_turn": 3,
        "roster_image": "tsunade.png"
    },
    {
        "name": "Naruo Uzumaki",
        "team": "akatsuki",
        "hp": 67,
        "mp": 22,
        "extra_mp": 5,
        "xp": 4,
        "available_from_turn": 2,
        "available_until_turn": 4,
        "roster_image": "naruto_uzumaki_deck_3.png"
    }
]